asterkit/__init__.py
asterkit/ami.py
asterkit/utils.py
asterkit/version.py
asterkit/agi/__init__.py
asterkit/agi/server.py
asterkit/ari/__init__.py
asterkit/ari/client.py
asterkit/ari/exceptions.py
asterkit/ari/models.py
asterkit-0.1b1.dist-info/AUTHORS
asterkit-0.1b1.dist-info/LICENSE
asterkit-0.1b1.dist-info/METADATA
asterkit-0.1b1.dist-info/WHEEL
asterkit-0.1b1.dist-info/top_level.txt
asterkit-0.1b1.dist-info/RECORD
