Metadata-Version: 2.1
Name: asterkit
Version: 0.1b1
Summary: This is a asynchronous Python library for Asterisk to work with ARI, AMI and AGI.
Home-page: https://gitlab.com/djbaldey/asterkit/
Author: Grigoriy Kramarenko
Author-email: root@rosix.ru
License: BSD License
Platform: any
Classifier: Development Status :: 4 - Beta
Classifier: Intended Audience :: Developers
Classifier: Intended Audience :: Telecommunications Industry
Classifier: License :: OSI Approved :: BSD License
Classifier: Operating System :: POSIX
Classifier: Operating System :: POSIX :: Linux
Classifier: Programming Language :: Python
Classifier: Programming Language :: Python :: 3
Classifier: Programming Language :: Python :: 3.7
Classifier: Programming Language :: Python :: 3.8
Classifier: Programming Language :: Python :: 3.9
Classifier: Programming Language :: Python :: 3.10
Classifier: Topic :: Communications :: Internet Phone
Classifier: Topic :: Communications :: Telephony
Requires-Dist: aiohttp (<3.9.0a,>=3.8.0)
Requires-Dist: pytz
